<annotation>
	<folder>images</folder>
	<filename>tank-00000255.jpg</filename>
	<path>D:\dataset\tank\2\images\tank-00000255.jpg</path>
	<source>
		<database>Unknown</database>
	</source>
	<size>
		<width>1024</width>
		<height>1024</height>
		<depth>3</depth>
	</size>
	<segmented>0</segmented>
	<object>
		<name>tank</name>
		<pose>Unspecified</pose>
		<truncated>0</truncated>
		<difficult>0</difficult>
		<bndbox>
			<xmin>558</xmin>
			<ymin>361</ymin>
			<xmax>622</xmax>
			<ymax>443</ymax>
		</bndbox>
	</object>
	<object>
		<name>tank</name>
		<pose>Unspecified</pose>
		<truncated>0</truncated>
		<difficult>0</difficult>
		<bndbox>
			<xmin>512</xmin>
			<ymin>329</ymin>
			<xmax>581</xmax>
			<ymax>420</ymax>
		</bndbox>
	</object>
	<object>
		<name>tank</name>
		<pose>Unspecified</pose>
		<truncated>0</truncated>
		<difficult>0</difficult>
		<bndbox>
			<xmin>472</xmin>
			<ymin>299</ymin>
			<xmax>542</xmax>
			<ymax>391</ymax>
		</bndbox>
	</object>
</annotation>
