<annotation>
	<folder>images</folder>
	<filename>tank-00000783.jpg</filename>
	<path>G:\dataset\tank\5\images\tank-00000783.jpg</path>
	<source>
		<database>Unknown</database>
	</source>
	<size>
		<width>1024</width>
		<height>1024</height>
		<depth>3</depth>
	</size>
	<segmented>0</segmented>
	<object>
		<name>tank</name>
		<pose>Unspecified</pose>
		<truncated>0</truncated>
		<difficult>0</difficult>
		<bndbox>
			<xmin>291</xmin>
			<ymin>113</ymin>
			<xmax>407</xmax>
			<ymax>186</ymax>
		</bndbox>
	</object>
	<object>
		<name>tank</name>
		<pose>Unspecified</pose>
		<truncated>0</truncated>
		<difficult>0</difficult>
		<bndbox>
			<xmin>245</xmin>
			<ymin>258</ymin>
			<xmax>366</xmax>
			<ymax>322</ymax>
		</bndbox>
	</object>
	<object>
		<name>tank</name>
		<pose>Unspecified</pose>
		<truncated>0</truncated>
		<difficult>0</difficult>
		<bndbox>
			<xmin>230</xmin>
			<ymin>314</ymin>
			<xmax>353</xmax>
			<ymax>373</ymax>
		</bndbox>
	</object>
	<object>
		<name>tank</name>
		<pose>Unspecified</pose>
		<truncated>0</truncated>
		<difficult>0</difficult>
		<bndbox>
			<xmin>216</xmin>
			<ymin>369</ymin>
			<xmax>331</xmax>
			<ymax>429</ymax>
		</bndbox>
	</object>
	<object>
		<name>tank</name>
		<pose>Unspecified</pose>
		<truncated>0</truncated>
		<difficult>0</difficult>
		<bndbox>
			<xmin>343</xmin>
			<ymin>529</ymin>
			<xmax>399</xmax>
			<ymax>629</ymax>
		</bndbox>
	</object>
	<object>
		<name>tank</name>
		<pose>Unspecified</pose>
		<truncated>0</truncated>
		<difficult>0</difficult>
		<bndbox>
			<xmin>392</xmin>
			<ymin>547</ymin>
			<xmax>452</xmax>
			<ymax>642</ymax>
		</bndbox>
	</object>
	<object>
		<name>tank</name>
		<pose>Unspecified</pose>
		<truncated>0</truncated>
		<difficult>0</difficult>
		<bndbox>
			<xmin>447</xmin>
			<ymin>555</ymin>
			<xmax>503</xmax>
			<ymax>654</ymax>
		</bndbox>
	</object>
	<object>
		<name>tank</name>
		<pose>Unspecified</pose>
		<truncated>0</truncated>
		<difficult>0</difficult>
		<bndbox>
			<xmin>501</xmin>
			<ymin>566</ymin>
			<xmax>558</xmax>
			<ymax>667</ymax>
		</bndbox>
	</object>
	<object>
		<name>tank</name>
		<pose>Unspecified</pose>
		<truncated>0</truncated>
		<difficult>0</difficult>
		<bndbox>
			<xmin>604</xmin>
			<ymin>588</ymin>
			<xmax>664</xmax>
			<ymax>688</ymax>
		</bndbox>
	</object>
</annotation>
