<annotation>
	<folder>images</folder>
	<filename>tank-00000700.jpg</filename>
	<path>G:\dataset\tank\5\images\tank-00000700.jpg</path>
	<source>
		<database>Unknown</database>
	</source>
	<size>
		<width>1024</width>
		<height>1024</height>
		<depth>3</depth>
	</size>
	<segmented>0</segmented>
	<object>
		<name>tank</name>
		<pose>Unspecified</pose>
		<truncated>0</truncated>
		<difficult>0</difficult>
		<bndbox>
			<xmin>451</xmin>
			<ymin>569</ymin>
			<xmax>584</xmax>
			<ymax>631</ymax>
		</bndbox>
	</object>
	<object>
		<name>tank</name>
		<pose>Unspecified</pose>
		<truncated>0</truncated>
		<difficult>0</difficult>
		<bndbox>
			<xmin>456</xmin>
			<ymin>481</ymin>
			<xmax>598</xmax>
			<ymax>542</ymax>
		</bndbox>
	</object>
	<object>
		<name>tank</name>
		<pose>Unspecified</pose>
		<truncated>0</truncated>
		<difficult>0</difficult>
		<bndbox>
			<xmin>459</xmin>
			<ymin>379</ymin>
			<xmax>616</xmax>
			<ymax>450</ymax>
		</bndbox>
	</object>
</annotation>
