<annotation>
	<folder>images</folder>
	<filename>tank-00000262.jpg</filename>
	<path>D:\dataset\tank\3\images\tank-00000262.jpg</path>
	<source>
		<database>Unknown</database>
	</source>
	<size>
		<width>1024</width>
		<height>1024</height>
		<depth>3</depth>
	</size>
	<segmented>0</segmented>
	<object>
		<name>tank</name>
		<pose>Unspecified</pose>
		<truncated>0</truncated>
		<difficult>0</difficult>
		<bndbox>
			<xmin>420</xmin>
			<ymin>507</ymin>
			<xmax>480</xmax>
			<ymax>613</ymax>
		</bndbox>
	</object>
	<object>
		<name>tank</name>
		<pose>Unspecified</pose>
		<truncated>0</truncated>
		<difficult>0</difficult>
		<bndbox>
			<xmin>485</xmin>
			<ymin>476</ymin>
			<xmax>543</xmax>
			<ymax>575</ymax>
		</bndbox>
	</object>
</annotation>
