<annotation>
	<folder>0606</folder>
	<filename>069.png</filename>
	<path>C:\Users\HaHa\Desktop\0511_数据筛选\0606\069.png</path>
	<source>
		<database>Unknown</database>
	</source>
	<size>
		<width>2076</width>
		<height>1009</height>
		<depth>3</depth>
	</size>
	<segmented>0</segmented>
	<object>
		<name>runway</name>
		<pose>Unspecified</pose>
		<truncated>0</truncated>
		<difficult>0</difficult>
		<bndbox>
			<xmin>823</xmin>
			<ymin>480</ymin>
			<xmax>944</xmax>
			<ymax>576</ymax>
		</bndbox>
	</object>
</annotation>
